{
  "interests": [
    {
      "label": "Data Analysis",
      "image": {
        "src": "../../images/computadora.png",
        "alt": ""
      }
    },
    {
      "label": "Machine Learning",
      "image": {
        "src": "../../images/machine-learning.png",
        "alt": ""
      }
    },
    {
      "label": "Project Management",
      "image": {
        "src": "../../images/project-management.png",
        "alt": ""
      }
    },
    {
      "label": "Strategic Planning",
      "image": {
        "src": "../../images/planificacion.png",
        "alt": ""
      }
    },
    {
      "label": "Cloud Computing",
      "image": {
        "src": "../../images/servidor-en-la-nube.png",
        "alt": ""
      }
    },
    {
      "label": "Creativity",
      "image": {
        "src": "../../images/bombilla.png",
        "alt": ""
      }
    },
    {
      "label": "Communication",
      "image": {
        "src": "../../images/communications.png",
        "alt": ""
      }
    },
    {
      "label": "Learning Agility",
      "image": {
        "src": "../../images/computadora (1).png",
        "alt": ""
      }
    }
  ],
  "button": {
    "visible": true,
    "label": "+ Load More",
    "initiallyShownInterests": 5
  }
}
